tobacco/Bio.py
tobacco/SBU_geometry.py
tobacco/__init__.py
tobacco/__main__.py
tobacco/adjust_edges.py
tobacco/bbcif_properties.py
tobacco/ciftemplate2graph.py
tobacco/configuration.py
tobacco/cycle_cocyle.py
tobacco/make_topologies.py
tobacco/place_bbs.py
tobacco/reindex.py
tobacco/reindex_bb_cifs.py
tobacco/remove_dummy_atoms.py
tobacco/remove_net_charge.py
tobacco/scale.py
tobacco/scale_animation.py
tobacco/scaled_embedding2coords.py
tobacco/scrape_rcsr.py
tobacco/tobacco.py
tobacco/tools.py
tobacco/topo_pore_analysis.py
tobacco/vertex_edge_assign.py
tobacco/write_cifs.py
tobacco/data/.gitkeep
ToBaCco_Modified-3.1.2.dist-info/LICENSE
ToBaCco_Modified-3.1.2.dist-info/METADATA
ToBaCco_Modified-3.1.2.dist-info/WHEEL
ToBaCco_Modified-3.1.2.dist-info/entry_points.txt
ToBaCco_Modified-3.1.2.dist-info/top_level.txt
ToBaCco_Modified-3.1.2.dist-info/RECORD
